django_pluralize_ru/__init__.py
django_pluralize_ru/templatetags/__init__.py
django_pluralize_ru/templatetags/pluralize_ru.py
django_pluralize_ru-0.1.2.dist-info/LICENSE.txt
django_pluralize_ru-0.1.2.dist-info/METADATA
django_pluralize_ru-0.1.2.dist-info/WHEEL
django_pluralize_ru-0.1.2.dist-info/RECORD
